<?xml version="1.0" standalone="yes"?>
<ExceptionSolution>
  <Table1>
    <NeedCloseActiveWindows>False</NeedCloseActiveWindows>
    <AppFunctionName>Void editValue_KeyPress(System.Object, System.Windows.Forms.KeyPressEventArgs)</AppFunctionName>
    <AppModuleFileName>RCPart.dll</AppModuleFileName>
    <AppModuleNameSpace>SajetFilter</AppModuleNameSpace>
    <AppModuleClassName>fFilter</AppModuleClassName>
    <AppExceptionSolution>NA</AppExceptionSolution>
  </Table1>
  <Table1>
    <NeedCloseActiveWindows>False</NeedCloseActiveWindows>
    <AppFunctionName>Void FFilter_Load(System.Object, System.EventArgs)</AppFunctionName>
    <AppModuleFileName>RCPart.dll</AppModuleFileName>
    <AppModuleNameSpace>SajetFilter</AppModuleNameSpace>
    <AppModuleClassName>fFilter</AppModuleClassName>
    <AppExceptionSolution>NA</AppExceptionSolution>
  </Table1>
  <Table1>
    <NeedCloseActiveWindows>False</NeedCloseActiveWindows>
    <AppFunctionName>Void DgvData_CellClick(System.Object, System.Windows.Forms.DataGridViewCellEventArgs)</AppFunctionName>
    <AppModuleFileName>RCPart.dll</AppModuleFileName>
    <AppModuleNameSpace>SajetFilter</AppModuleNameSpace>
    <AppModuleClassName>fFilter</AppModuleClassName>
    <AppExceptionSolution>NA</AppExceptionSolution>
  </Table1>
  <Table1>
    <NeedCloseActiveWindows>False</NeedCloseActiveWindows>
    <AppFunctionName>Void CombRoute_SelectedIndexChanged(System.Object, System.EventArgs)</AppFunctionName>
    <AppModuleFileName>RCPart.dll</AppModuleFileName>
    <AppModuleNameSpace>RCPart</AppModuleNameSpace>
    <AppModuleClassName>fData</AppModuleClassName>
    <AppExceptionSolution>NA</AppExceptionSolution>
  </Table1>
</ExceptionSolution>